trianglepy/_triangle.cpython-36m-x86_64-linux-gnu.so
trianglepy/__init__.py
trianglepy/version.py
trianglepy/common.py
trianglepy/triangle.py
trianglepy-0.0.7.dist-info/metadata.json
trianglepy-0.0.7.dist-info/WHEEL
trianglepy-0.0.7.dist-info/top_level.txt
trianglepy-0.0.7.dist-info/DESCRIPTION.rst
trianglepy-0.0.7.dist-info/METADATA
trianglepy-0.0.7.dist-info/RECORD
